ifscfinder/__init__.py
ifscfinder/main.py
ifscfinder/utils.py
ifscfinder/data/ifsc.db
ifscfinder/examples/__init__.py
ifscfinder/examples/basic_usage.py
ifscfinder/examples/lookup_examples.py
ifscfinder-0.1.0.dist-info/METADATA
ifscfinder-0.1.0.dist-info/WHEEL
ifscfinder-0.1.0.dist-info/entry_points.txt
ifscfinder-0.1.0.dist-info/top_level.txt
ifscfinder-0.1.0.dist-info/RECORD
