Metadata-Version: 2.4
Name: ifscfinder
Version: 0.1.0
Summary: High-performance IFSC code lookup utilities backed by SQLite.
Author-email: Akshat Kotpalliwar <akshatkot@gmail.com>
Maintainer-email: Akshat Kotpalliwar <akshatkot@gmail.com>
License-Expression: LGPL-2.1
Project-URL: Homepage, https://github.com/IntegerAlex/IFSCFinder
Project-URL: Repository, https://github.com/IntegerAlex/IFSCFinder
Project-URL: Documentation, https://github.com/IntegerAlex/IFSCFinder/wiki
Project-URL: Bug Reports, https://github.com/IntegerAlex/IFSCFinder/issues
Keywords: ifsc,banking,lookup,sqlite,finance,indian-banks
Classifier: Development Status :: 4 - Beta
Classifier: Intended Audience :: Developers
Classifier: Operating System :: OS Independent
Classifier: Programming Language :: Python :: 3
Classifier: Programming Language :: Python :: 3.7
Classifier: Programming Language :: Python :: 3.8
Classifier: Programming Language :: Python :: 3.9
Classifier: Programming Language :: Python :: 3.10
Classifier: Programming Language :: Python :: 3.11
Classifier: Programming Language :: Python :: 3.12
Classifier: Topic :: Database
Classifier: Topic :: Software Development :: Libraries :: Python Modules
Classifier: Topic :: Office/Business :: Financial
Requires-Python: >=3.7
Provides-Extra: fastapi
Requires-Dist: fastapi>=0.68.0; extra == "fastapi"
Requires-Dist: starlette>=0.14.0; extra == "fastapi"
Provides-Extra: flask
Requires-Dist: flask>=1.0.0; extra == "flask"
Provides-Extra: django
Requires-Dist: django>=3.0.0; extra == "django"
Provides-Extra: web
Requires-Dist: fastapi>=0.68.0; extra == "web"
Requires-Dist: starlette>=0.14.0; extra == "web"
Requires-Dist: flask>=1.0.0; extra == "web"
Requires-Dist: django>=3.0.0; extra == "web"
Provides-Extra: dev
Requires-Dist: pytest>=6.0; extra == "dev"
Requires-Dist: pytest-asyncio>=0.18.0; extra == "dev"
Requires-Dist: black>=21.0.0; extra == "dev"
Requires-Dist: flake8>=3.8.0; extra == "dev"
Requires-Dist: mypy>=0.910; extra == "dev"
Requires-Dist: pre-commit>=2.15.0; extra == "dev"
Requires-Dist: build>=0.8.0; extra == "dev"
Requires-Dist: twine>=4.0.0; extra == "dev"
Provides-Extra: performance
Requires-Dist: orjson>=3.8.0; extra == "performance"
Requires-Dist: uvloop>=0.17.0; sys_platform != "win32" and extra == "performance"
Provides-Extra: all
Requires-Dist: fastapi>=0.68.0; extra == "all"
Requires-Dist: starlette>=0.14.0; extra == "all"
Requires-Dist: flask>=1.0.0; extra == "all"
Requires-Dist: django>=3.0.0; extra == "all"
Requires-Dist: orjson>=3.8.0; extra == "all"
Requires-Dist: uvloop>=0.17.0; sys_platform != "win32" and extra == "all"
